zipstreamer/__init__.py
zipstreamer/__version__.py
zipstreamer/compat.py
zipstreamer-0.1.3.dist-info/LICENSE.txt
zipstreamer-0.1.3.dist-info/METADATA
zipstreamer-0.1.3.dist-info/RECORD
zipstreamer-0.1.3.dist-info/WHEEL
zipstreamer-0.1.3.dist-info/top_level.txt
